graphlin/__init__.py
graphlin/_enums.py
graphlin/_exceptions.py
graphlin/changes.py
graphlin/configuration.py
graphlin/connection.py
graphlin/engine.py
graphlin/logging.py
graphlin/node.py
graphlin/py.typed
graphlin/registry.py
graphlin/serialization.py
graphlin/session.py
graphlin/utilities.py
graphlin-0.1.2.dist-info/METADATA
graphlin-0.1.2.dist-info/WHEEL
graphlin-0.1.2.dist-info/RECORD
