Metadata-Version: 2.1
Name: graphlin
Version: 0.1.2
Summary: An ORM for gremlin-based graph databases (e.g. AWS Neptune).
Author: Michael Statt
Author-email: michael.statt@modelyst.io
Requires-Python: >=3.9,<4.0
Classifier: Programming Language :: Python :: 3
Classifier: Programming Language :: Python :: 3.9
Classifier: Programming Language :: Python :: 3.10
Classifier: Programming Language :: Python :: 3.11
Classifier: Programming Language :: Python :: 3.12
Classifier: Programming Language :: Python :: 3.13
Requires-Dist: aiohttp (>=3.8.6,<4.0.0)
Requires-Dist: boto3 (>=1.28.74,<2.0.0)
Requires-Dist: docker (>=6.1.3,<7.0.0)
Requires-Dist: gremlinpython (>=3.7.0,<4.0.0)
Requires-Dist: pydantic (>=2.4.2,<3.0.0)
Requires-Dist: pydantic-settings (>=2.0.3,<3.0.0)
Requires-Dist: rich (>=13.6.0,<14.0.0)
